Metadata-Version: 2.1
Name: SGtSNEpiPy
Version: 1.0.7
Summary: SGtSNEpiPy is a Python interface for the SG-t-SNE-П algorithm, a powerful tool for visualizing large, sparse, stochastic graphs.
Author: ['Chenshuhao Qin', 'Yihua Zhong']
Author-email: cq27@duke.edu, yz737@duke.edu,
